MANIFEST.in
README.md
setup.py
rubrik_tool/SdRestClient.py
rubrik_tool/__init__.py
rubrik_tool/dictconfig.py
rubrik_tool/logging_utils.py
rubrik_tool/rubrik_tool.py
rubrik_tool/sdconf.py
rubrik_tool.egg-info/PKG-INFO
rubrik_tool.egg-info/SOURCES.txt
rubrik_tool.egg-info/dependency_links.txt
rubrik_tool.egg-info/entry_points.txt
rubrik_tool.egg-info/not-zip-safe
rubrik_tool.egg-info/requires.txt
rubrik_tool.egg-info/top_level.txt