Metadata-Version: 1.1
Name: rubrik-tool
Version: 0.5.1.0
Summary: Python wrappers for Rubrik's APIs
Home-page: http://github.com/scaledata/rubrik_tool
Author: Rubrik
Author-email: adam.goldberg@rubrik.com
License: MIT
Keywords: rubrik
Platform: UNKNOWN
Classifier: Programming Language :: Python :: 2.6
Classifier: Programming Language :: Python :: 2.7
